
{
  "http://mmoon.org/lang/heb/inventory/oh/Sense_ru_%D0%B4%D0%BE%D1%80%D0%BE%D0%B3%D0%BE%D0%B9" : {
    "http://mmoon.org/mmoon/core/senseDefinition" : [ {
        "value" : "\u0434\u043E\u0440\u043E\u0433\u043E\u0439",
        "lang" : "ru",
        "type" : "literal"
        }
      
      ],
    "http://purl.org/dc/elements/1.1/language" : [ {
        "value" : "ru",
        "type" : "literal"
        }
      
      ],
    "http://www.w3.org/1999/02/22-rdf-syntax-ns#type" : [ {
        "value" : "http://mmoon.org/mmoon/core/Sense",
        "type" : "uri"
        }
      
      ]
    }
  }
