
{
  "http://mmoon.org/lang/heb/inventory/oh/Sense_en_middle%3B%20%28physics%29%20medium%3B%20%28art%29%20solvent%3B%20%D7%91%D7%AA%D7%95%D7%95%D7%9A%20-%20in%20between" : {
    "http://mmoon.org/mmoon/core/senseDefinition" : [ {
        "value" : "middle; (physics) medium; (art) solvent; \u05D1\u05EA\u05D5\u05D5\u05DA - in between",
        "lang" : "en",
        "type" : "literal"
        }
      
      ],
    "http://purl.org/dc/elements/1.1/language" : [ {
        "value" : "en",
        "type" : "literal"
        }
      
      ],
    "http://www.w3.org/1999/02/22-rdf-syntax-ns#type" : [ {
        "value" : "http://mmoon.org/mmoon/core/Sense",
        "type" : "uri"
        }
      
      ]
    }
  }
